{
  "snapshots": [
    {
      "updatedAt": "2026-06-12T13:42:01.285Z",
      "standings": [
        {
          "rank": 1,
          "name": "יניב",
          "points": 4,
          "matchesPlayed": 2
        },
        {
          "rank": 2,
          "name": "אריאל",
          "points": 2,
          "matchesPlayed": 1
        },
        {
          "rank": 2,
          "name": "בר",
          "points": 2,
          "matchesPlayed": 2
        },
        {
          "rank": 4,
          "name": "בנימין",
          "points": 0,
          "matchesPlayed": 1
        },
        {
          "rank": 4,
          "name": "ניב",
          "points": 0,
          "matchesPlayed": 1
        },
        {
          "rank": 4,
          "name": "עומר",
          "points": 0,
          "matchesPlayed": 1
        },
        {
          "rank": 4,
          "name": "עומרי",
          "points": 0,
          "matchesPlayed": 0
        },
        {
          "rank": 4,
          "name": "פרטוש",
          "points": 0,
          "matchesPlayed": 0
        }
      ]
    },
    {
      "updatedAt": "2026-06-12T22:26:45.536Z",
      "standings": [
        {
          "rank": 1,
          "name": "יניב",
          "points": 5,
          "matchesPlayed": 3
        },
        {
          "rank": 2,
          "name": "אריאל",
          "points": 3,
          "matchesPlayed": 2
        },
        {
          "rank": 2,
          "name": "בר",
          "points": 3,
          "matchesPlayed": 3
        },
        {
          "rank": 4,
          "name": "בנימין",
          "points": 1,
          "matchesPlayed": 2
        },
        {
          "rank": 5,
          "name": "ניב",
          "points": 0,
          "matchesPlayed": 1
        },
        {
          "rank": 5,
          "name": "עומר",
          "points": 0,
          "matchesPlayed": 1
        },
        {
          "rank": 5,
          "name": "עומרי",
          "points": 0,
          "matchesPlayed": 0
        },
        {
          "rank": 5,
          "name": "פרטוש",
          "points": 0,
          "matchesPlayed": 0
        }
      ]
    },
    {
      "updatedAt": "2026-06-13T04:44:53.522Z",
      "standings": [
        {
          "rank": 1,
          "name": "יניב",
          "points": 5,
          "matchesPlayed": 3
        },
        {
          "rank": 2,
          "name": "אריאל",
          "points": 3,
          "matchesPlayed": 2
        },
        {
          "rank": 2,
          "name": "בר",
          "points": 3,
          "matchesPlayed": 4
        },
        {
          "rank": 4,
          "name": "עומרי",
          "points": 2,
          "matchesPlayed": 1
        },
        {
          "rank": 4,
          "name": "פרטוש",
          "points": 2,
          "matchesPlayed": 2
        },
        {
          "rank": 6,
          "name": "בנימין",
          "points": 1,
          "matchesPlayed": 2
        },
        {
          "rank": 7,
          "name": "ניב",
          "points": 0,
          "matchesPlayed": 1
        },
        {
          "rank": 7,
          "name": "עומר",
          "points": 0,
          "matchesPlayed": 1
        }
      ]
    },
    {
      "updatedAt": "2026-06-13T21:10:30.871Z",
      "standings": [
        {
          "rank": 1,
          "name": "אריאל",
          "points": 5,
          "matchesPlayed": 4
        },
        {
          "rank": 1,
          "name": "יניב",
          "points": 5,
          "matchesPlayed": 3
        },
        {
          "rank": 3,
          "name": "בר",
          "points": 3,
          "matchesPlayed": 4
        },
        {
          "rank": 4,
          "name": "ניב",
          "points": 2,
          "matchesPlayed": 3
        },
        {
          "rank": 4,
          "name": "עומרי",
          "points": 2,
          "matchesPlayed": 1
        },
        {
          "rank": 4,
          "name": "פרטוש",
          "points": 2,
          "matchesPlayed": 2
        },
        {
          "rank": 7,
          "name": "בנימין",
          "points": 1,
          "matchesPlayed": 2
        },
        {
          "rank": 8,
          "name": "עומר",
          "points": 0,
          "matchesPlayed": 1
        }
      ]
    },
    {
      "updatedAt": "2026-06-14T00:11:21.632Z",
      "standings": [
        {
          "rank": 1,
          "name": "אריאל",
          "points": 6,
          "matchesPlayed": 5
        },
        {
          "rank": 2,
          "name": "יניב",
          "points": 5,
          "matchesPlayed": 3
        },
        {
          "rank": 3,
          "name": "פרטוש",
          "points": 4,
          "matchesPlayed": 4
        },
        {
          "rank": 4,
          "name": "בר",
          "points": 3,
          "matchesPlayed": 4
        },
        {
          "rank": 4,
          "name": "עומרי",
          "points": 3,
          "matchesPlayed": 2
        },
        {
          "rank": 6,
          "name": "ניב",
          "points": 2,
          "matchesPlayed": 3
        },
        {
          "rank": 7,
          "name": "בנימין",
          "points": 1,
          "matchesPlayed": 2
        },
        {
          "rank": 8,
          "name": "עומר",
          "points": 0,
          "matchesPlayed": 1
        }
      ]
    },
    {
      "updatedAt": "2026-06-14T03:09:23.479Z",
      "standings": [
        {
          "rank": 1,
          "name": "אריאל",
          "points": 8,
          "matchesPlayed": 7
        },
        {
          "rank": 2,
          "name": "יניב",
          "points": 5,
          "matchesPlayed": 3
        },
        {
          "rank": 3,
          "name": "ניב",
          "points": 4,
          "matchesPlayed": 5
        },
        {
          "rank": 3,
          "name": "פרטוש",
          "points": 4,
          "matchesPlayed": 4
        },
        {
          "rank": 5,
          "name": "בר",
          "points": 3,
          "matchesPlayed": 4
        },
        {
          "rank": 5,
          "name": "עומרי",
          "points": 3,
          "matchesPlayed": 2
        },
        {
          "rank": 7,
          "name": "בנימין",
          "points": 1,
          "matchesPlayed": 2
        },
        {
          "rank": 8,
          "name": "עומר",
          "points": 0,
          "matchesPlayed": 1
        }
      ]
    },
    {
      "updatedAt": "2026-06-14T06:04:19.432Z",
      "standings": [
        {
          "rank": 1,
          "name": "אריאל",
          "points": 8,
          "matchesPlayed": 8
        },
        {
          "rank": 2,
          "name": "יניב",
          "points": 5,
          "matchesPlayed": 3
        },
        {
          "rank": 2,
          "name": "עומרי",
          "points": 5,
          "matchesPlayed": 3
        },
        {
          "rank": 4,
          "name": "ניב",
          "points": 4,
          "matchesPlayed": 5
        },
        {
          "rank": 4,
          "name": "פרטוש",
          "points": 4,
          "matchesPlayed": 4
        },
        {
          "rank": 6,
          "name": "בנימין",
          "points": 3,
          "matchesPlayed": 4
        },
        {
          "rank": 6,
          "name": "בר",
          "points": 3,
          "matchesPlayed": 4
        },
        {
          "rank": 8,
          "name": "עומר",
          "points": 0,
          "matchesPlayed": 1
        }
      ]
    },
    {
      "updatedAt": "2026-06-14T19:04:19.698Z",
      "standings": [
        {
          "rank": 1,
          "name": "אריאל",
          "points": 8,
          "matchesPlayed": 8
        },
        {
          "rank": 2,
          "name": "ניב",
          "points": 6,
          "matchesPlayed": 7
        },
        {
          "rank": 3,
          "name": "יניב",
          "points": 5,
          "matchesPlayed": 3
        },
        {
          "rank": 3,
          "name": "עומרי",
          "points": 5,
          "matchesPlayed": 4
        },
        {
          "rank": 5,
          "name": "פרטוש",
          "points": 4,
          "matchesPlayed": 4
        },
        {
          "rank": 6,
          "name": "בנימין",
          "points": 3,
          "matchesPlayed": 4
        },
        {
          "rank": 6,
          "name": "בר",
          "points": 3,
          "matchesPlayed": 4
        },
        {
          "rank": 8,
          "name": "עומר",
          "points": 2,
          "matchesPlayed": 2
        }
      ]
    },
    {
      "updatedAt": "2026-06-14T22:02:25.321Z",
      "standings": [
        {
          "rank": 1,
          "name": "אריאל",
          "points": 9,
          "matchesPlayed": 9
        },
        {
          "rank": 2,
          "name": "ניב",
          "points": 7,
          "matchesPlayed": 8
        },
        {
          "rank": 3,
          "name": "יניב",
          "points": 5,
          "matchesPlayed": 3
        },
        {
          "rank": 3,
          "name": "עומרי",
          "points": 5,
          "matchesPlayed": 4
        },
        {
          "rank": 5,
          "name": "בנימין",
          "points": 4,
          "matchesPlayed": 5
        },
        {
          "rank": 5,
          "name": "פרטוש",
          "points": 4,
          "matchesPlayed": 4
        },
        {
          "rank": 7,
          "name": "בר",
          "points": 3,
          "matchesPlayed": 4
        },
        {
          "rank": 7,
          "name": "עומר",
          "points": 3,
          "matchesPlayed": 3
        }
      ]
    },
    {
      "updatedAt": "2026-06-15T01:10:28.573Z",
      "standings": [
        {
          "rank": 1,
          "name": "אריאל",
          "points": 9,
          "matchesPlayed": 9
        },
        {
          "rank": 2,
          "name": "ניב",
          "points": 7,
          "matchesPlayed": 8
        },
        {
          "rank": 3,
          "name": "בנימין",
          "points": 6,
          "matchesPlayed": 6
        },
        {
          "rank": 4,
          "name": "יניב",
          "points": 5,
          "matchesPlayed": 3
        },
        {
          "rank": 4,
          "name": "עומר",
          "points": 5,
          "matchesPlayed": 4
        },
        {
          "rank": 4,
          "name": "עומרי",
          "points": 5,
          "matchesPlayed": 5
        },
        {
          "rank": 7,
          "name": "פרטוש",
          "points": 4,
          "matchesPlayed": 5
        },
        {
          "rank": 8,
          "name": "בר",
          "points": 3,
          "matchesPlayed": 4
        }
      ]
    },
    {
      "updatedAt": "2026-06-15T04:04:26.111Z",
      "standings": [
        {
          "rank": 1,
          "name": "אריאל",
          "points": 9,
          "matchesPlayed": 9
        },
        {
          "rank": 2,
          "name": "יניב",
          "points": 7,
          "matchesPlayed": 4
        },
        {
          "rank": 2,
          "name": "ניב",
          "points": 7,
          "matchesPlayed": 8
        },
        {
          "rank": 2,
          "name": "עומר",
          "points": 7,
          "matchesPlayed": 5
        },
        {
          "rank": 5,
          "name": "בנימין",
          "points": 6,
          "matchesPlayed": 6
        },
        {
          "rank": 6,
          "name": "עומרי",
          "points": 5,
          "matchesPlayed": 6
        },
        {
          "rank": 7,
          "name": "פרטוש",
          "points": 4,
          "matchesPlayed": 6
        },
        {
          "rank": 8,
          "name": "בר",
          "points": 3,
          "matchesPlayed": 4
        }
      ]
    },
    {
      "updatedAt": "2026-06-15T19:42:22.316Z",
      "standings": [
        {
          "rank": 1,
          "name": "אריאל",
          "points": 9,
          "matchesPlayed": 9
        },
        {
          "rank": 2,
          "name": "יניב",
          "points": 8,
          "matchesPlayed": 5
        },
        {
          "rank": 3,
          "name": "ניב",
          "points": 7,
          "matchesPlayed": 8
        },
        {
          "rank": 3,
          "name": "עומר",
          "points": 7,
          "matchesPlayed": 5
        },
        {
          "rank": 5,
          "name": "בנימין",
          "points": 6,
          "matchesPlayed": 6
        },
        {
          "rank": 5,
          "name": "עומרי",
          "points": 6,
          "matchesPlayed": 7
        },
        {
          "rank": 7,
          "name": "פרטוש",
          "points": 5,
          "matchesPlayed": 7
        },
        {
          "rank": 8,
          "name": "בר",
          "points": 4,
          "matchesPlayed": 5
        }
      ]
    },
    {
      "updatedAt": "2026-06-15T21:03:23.552Z",
      "standings": [
        {
          "rank": 1,
          "name": "אריאל",
          "points": 9,
          "matchesPlayed": 9
        },
        {
          "rank": 2,
          "name": "יניב",
          "points": 8,
          "matchesPlayed": 5
        },
        {
          "rank": 2,
          "name": "ניב",
          "points": 8,
          "matchesPlayed": 9
        },
        {
          "rank": 4,
          "name": "בנימין",
          "points": 7,
          "matchesPlayed": 7
        },
        {
          "rank": 4,
          "name": "עומר",
          "points": 7,
          "matchesPlayed": 5
        },
        {
          "rank": 4,
          "name": "עומרי",
          "points": 7,
          "matchesPlayed": 8
        },
        {
          "rank": 7,
          "name": "בר",
          "points": 5,
          "matchesPlayed": 6
        },
        {
          "rank": 7,
          "name": "פרטוש",
          "points": 5,
          "matchesPlayed": 7
        }
      ]
    },
    {
      "updatedAt": "2026-06-16T00:10:34.463Z",
      "standings": [
        {
          "rank": 1,
          "name": "אריאל",
          "points": 9,
          "matchesPlayed": 9
        },
        {
          "rank": 1,
          "name": "יניב",
          "points": 9,
          "matchesPlayed": 6
        },
        {
          "rank": 1,
          "name": "ניב",
          "points": 9,
          "matchesPlayed": 10
        },
        {
          "rank": 4,
          "name": "עומר",
          "points": 8,
          "matchesPlayed": 6
        },
        {
          "rank": 4,
          "name": "עומרי",
          "points": 8,
          "matchesPlayed": 9
        },
        {
          "rank": 6,
          "name": "בנימין",
          "points": 7,
          "matchesPlayed": 7
        },
        {
          "rank": 7,
          "name": "בר",
          "points": 5,
          "matchesPlayed": 6
        },
        {
          "rank": 7,
          "name": "פרטוש",
          "points": 5,
          "matchesPlayed": 7
        }
      ]
    },
    {
      "updatedAt": "2026-06-16T03:09:26.416Z",
      "standings": [
        {
          "rank": 1,
          "name": "אריאל",
          "points": 10,
          "matchesPlayed": 10
        },
        {
          "rank": 2,
          "name": "יניב",
          "points": 9,
          "matchesPlayed": 6
        },
        {
          "rank": 2,
          "name": "ניב",
          "points": 9,
          "matchesPlayed": 10
        },
        {
          "rank": 2,
          "name": "עומר",
          "points": 9,
          "matchesPlayed": 7
        },
        {
          "rank": 5,
          "name": "בנימין",
          "points": 8,
          "matchesPlayed": 8
        },
        {
          "rank": 5,
          "name": "עומרי",
          "points": 8,
          "matchesPlayed": 9
        },
        {
          "rank": 7,
          "name": "פרטוש",
          "points": 6,
          "matchesPlayed": 8
        },
        {
          "rank": 8,
          "name": "בר",
          "points": 5,
          "matchesPlayed": 6
        }
      ]
    },
    {
      "updatedAt": "2026-06-16T21:10:32.819Z",
      "standings": [
        {
          "rank": 1,
          "name": "ניב",
          "points": 11,
          "matchesPlayed": 11
        },
        {
          "rank": 1,
          "name": "עומר",
          "points": 11,
          "matchesPlayed": 8
        },
        {
          "rank": 3,
          "name": "אריאל",
          "points": 10,
          "matchesPlayed": 11
        },
        {
          "rank": 4,
          "name": "יניב",
          "points": 9,
          "matchesPlayed": 7
        },
        {
          "rank": 5,
          "name": "בנימין",
          "points": 8,
          "matchesPlayed": 8
        },
        {
          "rank": 5,
          "name": "עומרי",
          "points": 8,
          "matchesPlayed": 9
        },
        {
          "rank": 7,
          "name": "פרטוש",
          "points": 6,
          "matchesPlayed": 8
        },
        {
          "rank": 8,
          "name": "בר",
          "points": 5,
          "matchesPlayed": 6
        }
      ]
    },
    {
      "updatedAt": "2026-06-17T00:08:31.424Z",
      "standings": [
        {
          "rank": 1,
          "name": "עומר",
          "points": 13,
          "matchesPlayed": 10
        },
        {
          "rank": 2,
          "name": "יניב",
          "points": 11,
          "matchesPlayed": 8
        },
        {
          "rank": 2,
          "name": "ניב",
          "points": 11,
          "matchesPlayed": 11
        },
        {
          "rank": 4,
          "name": "אריאל",
          "points": 10,
          "matchesPlayed": 11
        },
        {
          "rank": 5,
          "name": "בנימין",
          "points": 8,
          "matchesPlayed": 9
        },
        {
          "rank": 5,
          "name": "עומרי",
          "points": 8,
          "matchesPlayed": 9
        },
        {
          "rank": 7,
          "name": "פרטוש",
          "points": 6,
          "matchesPlayed": 8
        },
        {
          "rank": 8,
          "name": "בר",
          "points": 5,
          "matchesPlayed": 6
        }
      ]
    },
    {
      "updatedAt": "2026-06-17T03:06:27.371Z",
      "standings": [
        {
          "rank": 1,
          "name": "עומר",
          "points": 13,
          "matchesPlayed": 10
        },
        {
          "rank": 2,
          "name": "יניב",
          "points": 11,
          "matchesPlayed": 8
        },
        {
          "rank": 2,
          "name": "ניב",
          "points": 11,
          "matchesPlayed": 11
        },
        {
          "rank": 4,
          "name": "אריאל",
          "points": 10,
          "matchesPlayed": 11
        },
        {
          "rank": 4,
          "name": "בנימין",
          "points": 10,
          "matchesPlayed": 10
        },
        {
          "rank": 6,
          "name": "עומרי",
          "points": 8,
          "matchesPlayed": 10
        },
        {
          "rank": 7,
          "name": "בר",
          "points": 7,
          "matchesPlayed": 7
        },
        {
          "rank": 8,
          "name": "פרטוש",
          "points": 6,
          "matchesPlayed": 9
        }
      ]
    },
    {
      "updatedAt": "2026-06-17T06:15:33.836Z",
      "standings": [
        {
          "rank": 1,
          "name": "עומר",
          "points": 15,
          "matchesPlayed": 11
        },
        {
          "rank": 2,
          "name": "יניב",
          "points": 11,
          "matchesPlayed": 8
        },
        {
          "rank": 2,
          "name": "ניב",
          "points": 11,
          "matchesPlayed": 11
        },
        {
          "rank": 4,
          "name": "אריאל",
          "points": 10,
          "matchesPlayed": 11
        },
        {
          "rank": 4,
          "name": "בנימין",
          "points": 10,
          "matchesPlayed": 11
        },
        {
          "rank": 6,
          "name": "עומרי",
          "points": 8,
          "matchesPlayed": 11
        },
        {
          "rank": 6,
          "name": "פרטוש",
          "points": 8,
          "matchesPlayed": 10
        },
        {
          "rank": 8,
          "name": "בר",
          "points": 7,
          "matchesPlayed": 7
        }
      ]
    },
    {
      "updatedAt": "2026-06-17T19:04:30.864Z",
      "standings": [
        {
          "rank": 1,
          "name": "עומר",
          "points": 15,
          "matchesPlayed": 11
        },
        {
          "rank": 2,
          "name": "יניב",
          "points": 12,
          "matchesPlayed": 9
        },
        {
          "rank": 3,
          "name": "אריאל",
          "points": 11,
          "matchesPlayed": 12
        },
        {
          "rank": 3,
          "name": "ניב",
          "points": 11,
          "matchesPlayed": 11
        },
        {
          "rank": 5,
          "name": "בנימין",
          "points": 10,
          "matchesPlayed": 11
        },
        {
          "rank": 6,
          "name": "פרטוש",
          "points": 9,
          "matchesPlayed": 11
        },
        {
          "rank": 7,
          "name": "בר",
          "points": 8,
          "matchesPlayed": 8
        },
        {
          "rank": 7,
          "name": "עומרי",
          "points": 8,
          "matchesPlayed": 11
        }
      ]
    },
    {
      "updatedAt": "2026-06-17T22:06:21.254Z",
      "standings": [
        {
          "rank": 1,
          "name": "עומר",
          "points": 15,
          "matchesPlayed": 11
        },
        {
          "rank": 2,
          "name": "בנימין",
          "points": 12,
          "matchesPlayed": 12
        },
        {
          "rank": 2,
          "name": "יניב",
          "points": 12,
          "matchesPlayed": 10
        },
        {
          "rank": 4,
          "name": "אריאל",
          "points": 11,
          "matchesPlayed": 12
        },
        {
          "rank": 4,
          "name": "ניב",
          "points": 11,
          "matchesPlayed": 11
        },
        {
          "rank": 6,
          "name": "בר",
          "points": 10,
          "matchesPlayed": 10
        },
        {
          "rank": 7,
          "name": "פרטוש",
          "points": 9,
          "matchesPlayed": 11
        },
        {
          "rank": 8,
          "name": "עומרי",
          "points": 8,
          "matchesPlayed": 11
        }
      ]
    },
    {
      "updatedAt": "2026-06-18T01:10:30.039Z",
      "standings": [
        {
          "rank": 1,
          "name": "עומר",
          "points": 15,
          "matchesPlayed": 11
        },
        {
          "rank": 2,
          "name": "ניב",
          "points": 13,
          "matchesPlayed": 12
        },
        {
          "rank": 3,
          "name": "בנימין",
          "points": 12,
          "matchesPlayed": 12
        },
        {
          "rank": 3,
          "name": "יניב",
          "points": 12,
          "matchesPlayed": 11
        },
        {
          "rank": 5,
          "name": "אריאל",
          "points": 11,
          "matchesPlayed": 12
        },
        {
          "rank": 6,
          "name": "בר",
          "points": 10,
          "matchesPlayed": 11
        },
        {
          "rank": 6,
          "name": "עומרי",
          "points": 10,
          "matchesPlayed": 12
        },
        {
          "rank": 8,
          "name": "פרטוש",
          "points": 9,
          "matchesPlayed": 11
        }
      ]
    },
    {
      "updatedAt": "2026-06-18T04:10:29.706Z",
      "standings": [
        {
          "rank": 1,
          "name": "עומר",
          "points": 15,
          "matchesPlayed": 12
        },
        {
          "rank": 2,
          "name": "יניב",
          "points": 14,
          "matchesPlayed": 12
        },
        {
          "rank": 3,
          "name": "ניב",
          "points": 13,
          "matchesPlayed": 12
        },
        {
          "rank": 4,
          "name": "בנימין",
          "points": 12,
          "matchesPlayed": 12
        },
        {
          "rank": 4,
          "name": "בר",
          "points": 12,
          "matchesPlayed": 12
        },
        {
          "rank": 6,
          "name": "אריאל",
          "points": 11,
          "matchesPlayed": 12
        },
        {
          "rank": 7,
          "name": "עומרי",
          "points": 10,
          "matchesPlayed": 12
        },
        {
          "rank": 8,
          "name": "פרטוש",
          "points": 9,
          "matchesPlayed": 12
        }
      ]
    },
    {
      "updatedAt": "2026-06-18T18:04:25.783Z",
      "standings": [
        {
          "rank": 1,
          "name": "עומר",
          "points": 16,
          "matchesPlayed": 13
        },
        {
          "rank": 2,
          "name": "יניב",
          "points": 14,
          "matchesPlayed": 12
        },
        {
          "rank": 2,
          "name": "ניב",
          "points": 14,
          "matchesPlayed": 13
        },
        {
          "rank": 4,
          "name": "בנימין",
          "points": 13,
          "matchesPlayed": 13
        },
        {
          "rank": 4,
          "name": "בר",
          "points": 13,
          "matchesPlayed": 13
        },
        {
          "rank": 6,
          "name": "אריאל",
          "points": 11,
          "matchesPlayed": 12
        },
        {
          "rank": 7,
          "name": "עומרי",
          "points": 10,
          "matchesPlayed": 12
        },
        {
          "rank": 8,
          "name": "פרטוש",
          "points": 9,
          "matchesPlayed": 12
        }
      ]
    },
    {
      "updatedAt": "2026-06-18T21:02:25.283Z",
      "standings": [
        {
          "rank": 1,
          "name": "ניב",
          "points": 16,
          "matchesPlayed": 14
        },
        {
          "rank": 1,
          "name": "עומר",
          "points": 16,
          "matchesPlayed": 13
        },
        {
          "rank": 3,
          "name": "יניב",
          "points": 14,
          "matchesPlayed": 13
        },
        {
          "rank": 4,
          "name": "אריאל",
          "points": 13,
          "matchesPlayed": 13
        },
        {
          "rank": 4,
          "name": "בנימין",
          "points": 13,
          "matchesPlayed": 13
        },
        {
          "rank": 4,
          "name": "בר",
          "points": 13,
          "matchesPlayed": 14
        },
        {
          "rank": 7,
          "name": "עומרי",
          "points": 10,
          "matchesPlayed": 12
        },
        {
          "rank": 8,
          "name": "פרטוש",
          "points": 9,
          "matchesPlayed": 12
        }
      ]
    },
    {
      "updatedAt": "2026-06-19T00:08:21.038Z",
      "standings": [
        {
          "rank": 1,
          "name": "ניב",
          "points": 16,
          "matchesPlayed": 15
        },
        {
          "rank": 1,
          "name": "עומר",
          "points": 16,
          "matchesPlayed": 13
        },
        {
          "rank": 3,
          "name": "אריאל",
          "points": 15,
          "matchesPlayed": 15
        },
        {
          "rank": 3,
          "name": "בנימין",
          "points": 15,
          "matchesPlayed": 14
        },
        {
          "rank": 5,
          "name": "יניב",
          "points": 14,
          "matchesPlayed": 13
        },
        {
          "rank": 6,
          "name": "בר",
          "points": 13,
          "matchesPlayed": 14
        },
        {
          "rank": 7,
          "name": "עומרי",
          "points": 10,
          "matchesPlayed": 12
        },
        {
          "rank": 8,
          "name": "פרטוש",
          "points": 9,
          "matchesPlayed": 12
        }
      ]
    },
    {
      "updatedAt": "2026-06-19T03:03:19.338Z",
      "standings": [
        {
          "rank": 1,
          "name": "יניב",
          "points": 16,
          "matchesPlayed": 15
        },
        {
          "rank": 1,
          "name": "ניב",
          "points": 16,
          "matchesPlayed": 15
        },
        {
          "rank": 1,
          "name": "עומר",
          "points": 16,
          "matchesPlayed": 13
        },
        {
          "rank": 4,
          "name": "אריאל",
          "points": 15,
          "matchesPlayed": 16
        },
        {
          "rank": 4,
          "name": "בנימין",
          "points": 15,
          "matchesPlayed": 14
        },
        {
          "rank": 4,
          "name": "בר",
          "points": 15,
          "matchesPlayed": 15
        },
        {
          "rank": 7,
          "name": "עומרי",
          "points": 10,
          "matchesPlayed": 12
        },
        {
          "rank": 8,
          "name": "פרטוש",
          "points": 9,
          "matchesPlayed": 12
        }
      ]
    },
    {
      "updatedAt": "2026-06-19T21:10:32.782Z",
      "standings": [
        {
          "rank": 1,
          "name": "יניב",
          "points": 16,
          "matchesPlayed": 15
        },
        {
          "rank": 1,
          "name": "ניב",
          "points": 16,
          "matchesPlayed": 15
        },
        {
          "rank": 1,
          "name": "עומר",
          "points": 16,
          "matchesPlayed": 13
        },
        {
          "rank": 4,
          "name": "אריאל",
          "points": 15,
          "matchesPlayed": 16
        },
        {
          "rank": 4,
          "name": "בנימין",
          "points": 15,
          "matchesPlayed": 15
        },
        {
          "rank": 4,
          "name": "בר",
          "points": 15,
          "matchesPlayed": 15
        },
        {
          "rank": 7,
          "name": "עומרי",
          "points": 12,
          "matchesPlayed": 14
        },
        {
          "rank": 8,
          "name": "פרטוש",
          "points": 11,
          "matchesPlayed": 13
        }
      ]
    },
    {
      "updatedAt": "2026-06-20T00:09:23.644Z",
      "standings": [
        {
          "rank": 1,
          "name": "אריאל",
          "points": 17,
          "matchesPlayed": 18
        },
        {
          "rank": 2,
          "name": "יניב",
          "points": 16,
          "matchesPlayed": 15
        },
        {
          "rank": 2,
          "name": "ניב",
          "points": 16,
          "matchesPlayed": 16
        },
        {
          "rank": 2,
          "name": "עומר",
          "points": 16,
          "matchesPlayed": 13
        },
        {
          "rank": 5,
          "name": "בנימין",
          "points": 15,
          "matchesPlayed": 15
        },
        {
          "rank": 5,
          "name": "בר",
          "points": 15,
          "matchesPlayed": 15
        },
        {
          "rank": 7,
          "name": "פרטוש",
          "points": 13,
          "matchesPlayed": 14
        },
        {
          "rank": 8,
          "name": "עומרי",
          "points": 12,
          "matchesPlayed": 14
        }
      ]
    },
    {
      "updatedAt": "2026-06-20T02:37:20.502Z",
      "standings": [
        {
          "rank": 1,
          "name": "אריאל",
          "points": 17,
          "matchesPlayed": 19
        },
        {
          "rank": 2,
          "name": "יניב",
          "points": 16,
          "matchesPlayed": 15
        },
        {
          "rank": 2,
          "name": "ניב",
          "points": 16,
          "matchesPlayed": 17
        },
        {
          "rank": 2,
          "name": "עומר",
          "points": 16,
          "matchesPlayed": 13
        },
        {
          "rank": 5,
          "name": "בנימין",
          "points": 15,
          "matchesPlayed": 15
        },
        {
          "rank": 5,
          "name": "בר",
          "points": 15,
          "matchesPlayed": 15
        },
        {
          "rank": 5,
          "name": "פרטוש",
          "points": 15,
          "matchesPlayed": 15
        },
        {
          "rank": 8,
          "name": "עומרי",
          "points": 14,
          "matchesPlayed": 15
        }
      ]
    },
    {
      "updatedAt": "2026-06-20T05:14:27.511Z",
      "standings": [
        {
          "rank": 1,
          "name": "אריאל",
          "points": 17,
          "matchesPlayed": 20
        },
        {
          "rank": 1,
          "name": "בר",
          "points": 17,
          "matchesPlayed": 16
        },
        {
          "rank": 1,
          "name": "פרטוש",
          "points": 17,
          "matchesPlayed": 16
        },
        {
          "rank": 4,
          "name": "יניב",
          "points": 16,
          "matchesPlayed": 15
        },
        {
          "rank": 4,
          "name": "ניב",
          "points": 16,
          "matchesPlayed": 17
        },
        {
          "rank": 4,
          "name": "עומר",
          "points": 16,
          "matchesPlayed": 13
        },
        {
          "rank": 7,
          "name": "בנימין",
          "points": 15,
          "matchesPlayed": 16
        },
        {
          "rank": 8,
          "name": "עומרי",
          "points": 14,
          "matchesPlayed": 15
        }
      ]
    },
    {
      "updatedAt": "2026-06-20T19:02:25.735Z",
      "standings": [
        {
          "rank": 1,
          "name": "אריאל",
          "points": 19,
          "matchesPlayed": 21
        },
        {
          "rank": 2,
          "name": "ניב",
          "points": 18,
          "matchesPlayed": 18
        },
        {
          "rank": 3,
          "name": "בר",
          "points": 17,
          "matchesPlayed": 16
        },
        {
          "rank": 3,
          "name": "פרטוש",
          "points": 17,
          "matchesPlayed": 16
        },
        {
          "rank": 5,
          "name": "יניב",
          "points": 16,
          "matchesPlayed": 16
        },
        {
          "rank": 5,
          "name": "עומר",
          "points": 16,
          "matchesPlayed": 14
        },
        {
          "rank": 7,
          "name": "בנימין",
          "points": 15,
          "matchesPlayed": 16
        },
        {
          "rank": 8,
          "name": "עומרי",
          "points": 14,
          "matchesPlayed": 15
        }
      ]
    },
    {
      "updatedAt": "2026-06-20T22:05:31.782Z",
      "standings": [
        {
          "rank": 1,
          "name": "ניב",
          "points": 20,
          "matchesPlayed": 19
        },
        {
          "rank": 2,
          "name": "אריאל",
          "points": 19,
          "matchesPlayed": 21
        },
        {
          "rank": 3,
          "name": "עומר",
          "points": 18,
          "matchesPlayed": 16
        },
        {
          "rank": 4,
          "name": "בר",
          "points": 17,
          "matchesPlayed": 16
        },
        {
          "rank": 4,
          "name": "פרטוש",
          "points": 17,
          "matchesPlayed": 16
        },
        {
          "rank": 6,
          "name": "יניב",
          "points": 16,
          "matchesPlayed": 16
        },
        {
          "rank": 7,
          "name": "בנימין",
          "points": 15,
          "matchesPlayed": 17
        },
        {
          "rank": 8,
          "name": "עומרי",
          "points": 14,
          "matchesPlayed": 15
        }
      ]
    },
    {
      "updatedAt": "2026-06-21T02:00:43.195Z",
      "standings": [
        {
          "rank": 1,
          "name": "ניב",
          "points": 21,
          "matchesPlayed": 20
        },
        {
          "rank": 2,
          "name": "אריאל",
          "points": 19,
          "matchesPlayed": 21
        },
        {
          "rank": 3,
          "name": "עומר",
          "points": 18,
          "matchesPlayed": 16
        },
        {
          "rank": 3,
          "name": "פרטוש",
          "points": 18,
          "matchesPlayed": 17
        },
        {
          "rank": 5,
          "name": "בר",
          "points": 17,
          "matchesPlayed": 16
        },
        {
          "rank": 6,
          "name": "יניב",
          "points": 16,
          "matchesPlayed": 16
        },
        {
          "rank": 6,
          "name": "עומרי",
          "points": 16,
          "matchesPlayed": 17
        },
        {
          "rank": 8,
          "name": "בנימין",
          "points": 15,
          "matchesPlayed": 17
        }
      ]
    },
    {
      "updatedAt": "2026-06-21T06:03:20.705Z",
      "standings": [
        {
          "rank": 1,
          "name": "ניב",
          "points": 21,
          "matchesPlayed": 20
        },
        {
          "rank": 2,
          "name": "עומר",
          "points": 20,
          "matchesPlayed": 17
        },
        {
          "rank": 3,
          "name": "אריאל",
          "points": 19,
          "matchesPlayed": 21
        },
        {
          "rank": 4,
          "name": "פרטוש",
          "points": 18,
          "matchesPlayed": 18
        },
        {
          "rank": 5,
          "name": "בנימין",
          "points": 17,
          "matchesPlayed": 18
        },
        {
          "rank": 5,
          "name": "בר",
          "points": 17,
          "matchesPlayed": 16
        },
        {
          "rank": 7,
          "name": "יניב",
          "points": 16,
          "matchesPlayed": 16
        },
        {
          "rank": 7,
          "name": "עומרי",
          "points": 16,
          "matchesPlayed": 18
        }
      ]
    },
    {
      "updatedAt": "2026-06-21T18:08:24.021Z",
      "standings": [
        {
          "rank": 1,
          "name": "ניב",
          "points": 21,
          "matchesPlayed": 20
        },
        {
          "rank": 2,
          "name": "עומר",
          "points": 20,
          "matchesPlayed": 18
        },
        {
          "rank": 3,
          "name": "אריאל",
          "points": 19,
          "matchesPlayed": 21
        },
        {
          "rank": 4,
          "name": "יניב",
          "points": 18,
          "matchesPlayed": 18
        },
        {
          "rank": 4,
          "name": "עומרי",
          "points": 18,
          "matchesPlayed": 19
        },
        {
          "rank": 4,
          "name": "פרטוש",
          "points": 18,
          "matchesPlayed": 18
        },
        {
          "rank": 7,
          "name": "בנימין",
          "points": 17,
          "matchesPlayed": 18
        },
        {
          "rank": 7,
          "name": "בר",
          "points": 17,
          "matchesPlayed": 16
        }
      ]
    },
    {
      "updatedAt": "2026-06-21T21:07:26.274Z",
      "standings": [
        {
          "rank": 1,
          "name": "ניב",
          "points": 21,
          "matchesPlayed": 20
        },
        {
          "rank": 1,
          "name": "עומר",
          "points": 21,
          "matchesPlayed": 19
        },
        {
          "rank": 3,
          "name": "אריאל",
          "points": 19,
          "matchesPlayed": 21
        },
        {
          "rank": 3,
          "name": "בנימין",
          "points": 19,
          "matchesPlayed": 20
        },
        {
          "rank": 3,
          "name": "עומרי",
          "points": 19,
          "matchesPlayed": 20
        },
        {
          "rank": 6,
          "name": "יניב",
          "points": 18,
          "matchesPlayed": 18
        },
        {
          "rank": 6,
          "name": "פרטוש",
          "points": 18,
          "matchesPlayed": 18
        },
        {
          "rank": 8,
          "name": "בר",
          "points": 17,
          "matchesPlayed": 16
        }
      ]
    },
    {
      "updatedAt": "2026-06-22T00:11:21.678Z",
      "standings": [
        {
          "rank": 1,
          "name": "ניב",
          "points": 22,
          "matchesPlayed": 21
        },
        {
          "rank": 2,
          "name": "עומר",
          "points": 21,
          "matchesPlayed": 19
        },
        {
          "rank": 3,
          "name": "עומרי",
          "points": 20,
          "matchesPlayed": 21
        },
        {
          "rank": 4,
          "name": "אריאל",
          "points": 19,
          "matchesPlayed": 21
        },
        {
          "rank": 4,
          "name": "בנימין",
          "points": 19,
          "matchesPlayed": 20
        },
        {
          "rank": 4,
          "name": "פרטוש",
          "points": 19,
          "matchesPlayed": 19
        },
        {
          "rank": 7,
          "name": "בר",
          "points": 18,
          "matchesPlayed": 17
        },
        {
          "rank": 7,
          "name": "יניב",
          "points": 18,
          "matchesPlayed": 18
        }
      ]
    },
    {
      "updatedAt": "2026-06-22T03:07:24.458Z",
      "standings": [
        {
          "rank": 1,
          "name": "ניב",
          "points": 24,
          "matchesPlayed": 22
        },
        {
          "rank": 2,
          "name": "עומר",
          "points": 21,
          "matchesPlayed": 19
        },
        {
          "rank": 3,
          "name": "בר",
          "points": 20,
          "matchesPlayed": 18
        },
        {
          "rank": 3,
          "name": "עומרי",
          "points": 20,
          "matchesPlayed": 21
        },
        {
          "rank": 5,
          "name": "אריאל",
          "points": 19,
          "matchesPlayed": 22
        },
        {
          "rank": 5,
          "name": "בנימין",
          "points": 19,
          "matchesPlayed": 20
        },
        {
          "rank": 5,
          "name": "פרטוש",
          "points": 19,
          "matchesPlayed": 20
        },
        {
          "rank": 8,
          "name": "יניב",
          "points": 18,
          "matchesPlayed": 18
        }
      ]
    },
    {
      "updatedAt": "2026-06-22T19:07:31.182Z",
      "standings": [
        {
          "rank": 1,
          "name": "ניב",
          "points": 24,
          "matchesPlayed": 22
        },
        {
          "rank": 2,
          "name": "בר",
          "points": 22,
          "matchesPlayed": 19
        },
        {
          "rank": 3,
          "name": "בנימין",
          "points": 21,
          "matchesPlayed": 21
        },
        {
          "rank": 3,
          "name": "עומר",
          "points": 21,
          "matchesPlayed": 20
        },
        {
          "rank": 5,
          "name": "עומרי",
          "points": 20,
          "matchesPlayed": 21
        },
        {
          "rank": 6,
          "name": "אריאל",
          "points": 19,
          "matchesPlayed": 22
        },
        {
          "rank": 6,
          "name": "פרטוש",
          "points": 19,
          "matchesPlayed": 21
        },
        {
          "rank": 8,
          "name": "יניב",
          "points": 18,
          "matchesPlayed": 18
        }
      ]
    },
    {
      "updatedAt": "2026-06-23T00:55:25.587Z",
      "standings": [
        {
          "rank": 1,
          "name": "ניב",
          "points": 26,
          "matchesPlayed": 23
        },
        {
          "rank": 2,
          "name": "עומר",
          "points": 23,
          "matchesPlayed": 22
        },
        {
          "rank": 3,
          "name": "בר",
          "points": 22,
          "matchesPlayed": 19
        },
        {
          "rank": 4,
          "name": "בנימין",
          "points": 21,
          "matchesPlayed": 22
        },
        {
          "rank": 5,
          "name": "עומרי",
          "points": 20,
          "matchesPlayed": 21
        },
        {
          "rank": 6,
          "name": "אריאל",
          "points": 19,
          "matchesPlayed": 22
        },
        {
          "rank": 6,
          "name": "פרטוש",
          "points": 19,
          "matchesPlayed": 21
        },
        {
          "rank": 8,
          "name": "יניב",
          "points": 18,
          "matchesPlayed": 18
        }
      ]
    },
    {
      "updatedAt": "2026-06-23T02:06:24.700Z",
      "standings": [
        {
          "rank": 1,
          "name": "ניב",
          "points": 26,
          "matchesPlayed": 23
        },
        {
          "rank": 2,
          "name": "עומר",
          "points": 25,
          "matchesPlayed": 23
        },
        {
          "rank": 3,
          "name": "בר",
          "points": 22,
          "matchesPlayed": 19
        },
        {
          "rank": 4,
          "name": "בנימין",
          "points": 21,
          "matchesPlayed": 22
        },
        {
          "rank": 5,
          "name": "יניב",
          "points": 20,
          "matchesPlayed": 20
        },
        {
          "rank": 5,
          "name": "עומרי",
          "points": 20,
          "matchesPlayed": 21
        },
        {
          "rank": 7,
          "name": "אריאל",
          "points": 19,
          "matchesPlayed": 23
        },
        {
          "rank": 7,
          "name": "פרטוש",
          "points": 19,
          "matchesPlayed": 21
        }
      ]
    },
    {
      "updatedAt": "2026-06-23T05:07:20.140Z",
      "standings": [
        {
          "rank": 1,
          "name": "ניב",
          "points": 26,
          "matchesPlayed": 23
        },
        {
          "rank": 2,
          "name": "עומר",
          "points": 25,
          "matchesPlayed": 23
        },
        {
          "rank": 3,
          "name": "בר",
          "points": 22,
          "matchesPlayed": 19
        },
        {
          "rank": 3,
          "name": "עומרי",
          "points": 22,
          "matchesPlayed": 23
        },
        {
          "rank": 5,
          "name": "בנימין",
          "points": 21,
          "matchesPlayed": 23
        },
        {
          "rank": 5,
          "name": "פרטוש",
          "points": 21,
          "matchesPlayed": 22
        },
        {
          "rank": 7,
          "name": "יניב",
          "points": 20,
          "matchesPlayed": 20
        },
        {
          "rank": 8,
          "name": "אריאל",
          "points": 19,
          "matchesPlayed": 23
        }
      ]
    },
    {
      "updatedAt": "2026-06-23T19:05:36.450Z",
      "standings": [
        {
          "rank": 1,
          "name": "ניב",
          "points": 26,
          "matchesPlayed": 23
        },
        {
          "rank": 2,
          "name": "עומר",
          "points": 25,
          "matchesPlayed": 24
        },
        {
          "rank": 3,
          "name": "פרטוש",
          "points": 23,
          "matchesPlayed": 24
        },
        {
          "rank": 4,
          "name": "בר",
          "points": 22,
          "matchesPlayed": 19
        },
        {
          "rank": 4,
          "name": "עומרי",
          "points": 22,
          "matchesPlayed": 23
        },
        {
          "rank": 6,
          "name": "אריאל",
          "points": 21,
          "matchesPlayed": 24
        },
        {
          "rank": 6,
          "name": "בנימין",
          "points": 21,
          "matchesPlayed": 23
        },
        {
          "rank": 8,
          "name": "יניב",
          "points": 20,
          "matchesPlayed": 20
        }
      ]
    },
    {
      "updatedAt": "2026-06-23T22:05:44.418Z",
      "standings": [
        {
          "rank": 1,
          "name": "ניב",
          "points": 27,
          "matchesPlayed": 24
        },
        {
          "rank": 2,
          "name": "עומר",
          "points": 25,
          "matchesPlayed": 24
        },
        {
          "rank": 3,
          "name": "בר",
          "points": 23,
          "matchesPlayed": 20
        },
        {
          "rank": 3,
          "name": "עומרי",
          "points": 23,
          "matchesPlayed": 24
        },
        {
          "rank": 3,
          "name": "פרטוש",
          "points": 23,
          "matchesPlayed": 24
        },
        {
          "rank": 6,
          "name": "בנימין",
          "points": 22,
          "matchesPlayed": 24
        },
        {
          "rank": 7,
          "name": "אריאל",
          "points": 21,
          "matchesPlayed": 24
        },
        {
          "rank": 8,
          "name": "יניב",
          "points": 20,
          "matchesPlayed": 20
        }
      ]
    },
    {
      "updatedAt": "2026-06-24T00:59:18.856Z",
      "standings": [
        {
          "rank": 1,
          "name": "ניב",
          "points": 27,
          "matchesPlayed": 24
        },
        {
          "rank": 2,
          "name": "בר",
          "points": 25,
          "matchesPlayed": 22
        },
        {
          "rank": 2,
          "name": "עומר",
          "points": 25,
          "matchesPlayed": 24
        },
        {
          "rank": 4,
          "name": "עומרי",
          "points": 23,
          "matchesPlayed": 24
        },
        {
          "rank": 4,
          "name": "פרטוש",
          "points": 23,
          "matchesPlayed": 24
        },
        {
          "rank": 6,
          "name": "בנימין",
          "points": 22,
          "matchesPlayed": 24
        },
        {
          "rank": 6,
          "name": "יניב",
          "points": 22,
          "matchesPlayed": 22
        },
        {
          "rank": 8,
          "name": "אריאל",
          "points": 21,
          "matchesPlayed": 24
        }
      ]
    },
    {
      "updatedAt": "2026-06-24T04:03:19.771Z",
      "standings": [
        {
          "rank": 1,
          "name": "בר",
          "points": 27,
          "matchesPlayed": 24
        },
        {
          "rank": 1,
          "name": "ניב",
          "points": 27,
          "matchesPlayed": 24
        },
        {
          "rank": 3,
          "name": "עומר",
          "points": 25,
          "matchesPlayed": 24
        },
        {
          "rank": 4,
          "name": "יניב",
          "points": 24,
          "matchesPlayed": 24
        },
        {
          "rank": 5,
          "name": "עומרי",
          "points": 23,
          "matchesPlayed": 24
        },
        {
          "rank": 5,
          "name": "פרטוש",
          "points": 23,
          "matchesPlayed": 24
        },
        {
          "rank": 7,
          "name": "בנימין",
          "points": 22,
          "matchesPlayed": 24
        },
        {
          "rank": 8,
          "name": "אריאל",
          "points": 21,
          "matchesPlayed": 24
        }
      ]
    },
    {
      "updatedAt": "2026-06-24T21:01:21.582Z",
      "standings": [
        {
          "rank": 1,
          "name": "ניב",
          "points": 29,
          "matchesPlayed": 25
        },
        {
          "rank": 2,
          "name": "בר",
          "points": 27,
          "matchesPlayed": 24
        },
        {
          "rank": 3,
          "name": "עומר",
          "points": 25,
          "matchesPlayed": 24
        },
        {
          "rank": 4,
          "name": "יניב",
          "points": 24,
          "matchesPlayed": 24
        },
        {
          "rank": 5,
          "name": "אריאל",
          "points": 23,
          "matchesPlayed": 26
        },
        {
          "rank": 5,
          "name": "עומרי",
          "points": 23,
          "matchesPlayed": 24
        },
        {
          "rank": 5,
          "name": "פרטוש",
          "points": 23,
          "matchesPlayed": 24
        },
        {
          "rank": 8,
          "name": "בנימין",
          "points": 22,
          "matchesPlayed": 25
        }
      ]
    },
    {
      "updatedAt": "2026-06-24T21:04:25.057Z",
      "standings": [
        {
          "rank": 1,
          "name": "בר",
          "points": 29,
          "matchesPlayed": 25
        },
        {
          "rank": 1,
          "name": "ניב",
          "points": 29,
          "matchesPlayed": 26
        },
        {
          "rank": 3,
          "name": "יניב",
          "points": 26,
          "matchesPlayed": 25
        },
        {
          "rank": 4,
          "name": "עומר",
          "points": 25,
          "matchesPlayed": 24
        },
        {
          "rank": 5,
          "name": "אריאל",
          "points": 23,
          "matchesPlayed": 27
        },
        {
          "rank": 5,
          "name": "עומרי",
          "points": 23,
          "matchesPlayed": 24
        },
        {
          "rank": 5,
          "name": "פרטוש",
          "points": 23,
          "matchesPlayed": 24
        },
        {
          "rank": 8,
          "name": "בנימין",
          "points": 22,
          "matchesPlayed": 25
        }
      ]
    },
    {
      "updatedAt": "2026-06-25T00:06:25.993Z",
      "standings": [
        {
          "rank": 1,
          "name": "בר",
          "points": 29,
          "matchesPlayed": 25
        },
        {
          "rank": 1,
          "name": "ניב",
          "points": 29,
          "matchesPlayed": 27
        },
        {
          "rank": 3,
          "name": "יניב",
          "points": 26,
          "matchesPlayed": 25
        },
        {
          "rank": 4,
          "name": "אריאל",
          "points": 25,
          "matchesPlayed": 29
        },
        {
          "rank": 4,
          "name": "עומר",
          "points": 25,
          "matchesPlayed": 24
        },
        {
          "rank": 4,
          "name": "פרטוש",
          "points": 25,
          "matchesPlayed": 25
        },
        {
          "rank": 7,
          "name": "עומרי",
          "points": 23,
          "matchesPlayed": 24
        },
        {
          "rank": 8,
          "name": "בנימין",
          "points": 22,
          "matchesPlayed": 25
        }
      ]
    },
    {
      "updatedAt": "2026-06-25T00:07:26.630Z",
      "standings": [
        {
          "rank": 1,
          "name": "בר",
          "points": 29,
          "matchesPlayed": 25
        },
        {
          "rank": 1,
          "name": "ניב",
          "points": 29,
          "matchesPlayed": 28
        },
        {
          "rank": 3,
          "name": "פרטוש",
          "points": 27,
          "matchesPlayed": 26
        },
        {
          "rank": 4,
          "name": "יניב",
          "points": 26,
          "matchesPlayed": 25
        },
        {
          "rank": 5,
          "name": "אריאל",
          "points": 25,
          "matchesPlayed": 30
        },
        {
          "rank": 5,
          "name": "עומר",
          "points": 25,
          "matchesPlayed": 24
        },
        {
          "rank": 5,
          "name": "עומרי",
          "points": 25,
          "matchesPlayed": 25
        },
        {
          "rank": 8,
          "name": "בנימין",
          "points": 22,
          "matchesPlayed": 25
        }
      ]
    },
    {
      "updatedAt": "2026-06-25T03:02:21.138Z",
      "standings": [
        {
          "rank": 1,
          "name": "בר",
          "points": 31,
          "matchesPlayed": 27
        },
        {
          "rank": 1,
          "name": "ניב",
          "points": 31,
          "matchesPlayed": 29
        },
        {
          "rank": 3,
          "name": "יניב",
          "points": 28,
          "matchesPlayed": 27
        },
        {
          "rank": 4,
          "name": "עומר",
          "points": 27,
          "matchesPlayed": 25
        },
        {
          "rank": 4,
          "name": "פרטוש",
          "points": 27,
          "matchesPlayed": 26
        },
        {
          "rank": 6,
          "name": "אריאל",
          "points": 25,
          "matchesPlayed": 31
        },
        {
          "rank": 6,
          "name": "עומרי",
          "points": 25,
          "matchesPlayed": 25
        },
        {
          "rank": 8,
          "name": "בנימין",
          "points": 22,
          "matchesPlayed": 26
        }
      ]
    },
    {
      "updatedAt": "2026-06-25T22:03:23.222Z",
      "standings": [
        {
          "rank": 1,
          "name": "בר",
          "points": 31,
          "matchesPlayed": 27
        },
        {
          "rank": 1,
          "name": "ניב",
          "points": 31,
          "matchesPlayed": 31
        },
        {
          "rank": 3,
          "name": "עומר",
          "points": 29,
          "matchesPlayed": 27
        },
        {
          "rank": 3,
          "name": "פרטוש",
          "points": 29,
          "matchesPlayed": 27
        },
        {
          "rank": 5,
          "name": "יניב",
          "points": 28,
          "matchesPlayed": 27
        },
        {
          "rank": 6,
          "name": "עומרי",
          "points": 27,
          "matchesPlayed": 27
        },
        {
          "rank": 7,
          "name": "אריאל",
          "points": 25,
          "matchesPlayed": 31
        },
        {
          "rank": 8,
          "name": "בנימין",
          "points": 24,
          "matchesPlayed": 27
        }
      ]
    },
    {
      "updatedAt": "2026-06-26T01:00:40.376Z",
      "standings": [
        {
          "rank": 1,
          "name": "ניב",
          "points": 33,
          "matchesPlayed": 32
        },
        {
          "rank": 2,
          "name": "בר",
          "points": 31,
          "matchesPlayed": 27
        },
        {
          "rank": 3,
          "name": "עומר",
          "points": 29,
          "matchesPlayed": 27
        },
        {
          "rank": 3,
          "name": "פרטוש",
          "points": 29,
          "matchesPlayed": 28
        },
        {
          "rank": 5,
          "name": "יניב",
          "points": 28,
          "matchesPlayed": 27
        },
        {
          "rank": 6,
          "name": "אריאל",
          "points": 27,
          "matchesPlayed": 32
        },
        {
          "rank": 6,
          "name": "עומרי",
          "points": 27,
          "matchesPlayed": 28
        },
        {
          "rank": 8,
          "name": "בנימין",
          "points": 24,
          "matchesPlayed": 27
        }
      ]
    },
    {
      "updatedAt": "2026-06-26T01:03:23.437Z",
      "standings": [
        {
          "rank": 1,
          "name": "ניב",
          "points": 33,
          "matchesPlayed": 32
        },
        {
          "rank": 2,
          "name": "בר",
          "points": 31,
          "matchesPlayed": 27
        },
        {
          "rank": 2,
          "name": "עומר",
          "points": 31,
          "matchesPlayed": 29
        },
        {
          "rank": 4,
          "name": "יניב",
          "points": 29,
          "matchesPlayed": 28
        },
        {
          "rank": 4,
          "name": "פרטוש",
          "points": 29,
          "matchesPlayed": 28
        },
        {
          "rank": 6,
          "name": "אריאל",
          "points": 27,
          "matchesPlayed": 32
        },
        {
          "rank": 6,
          "name": "עומרי",
          "points": 27,
          "matchesPlayed": 28
        },
        {
          "rank": 8,
          "name": "בנימין",
          "points": 25,
          "matchesPlayed": 28
        }
      ]
    },
    {
      "updatedAt": "2026-06-26T04:04:22.302Z",
      "standings": [
        {
          "rank": 1,
          "name": "ניב",
          "points": 33,
          "matchesPlayed": 32
        },
        {
          "rank": 2,
          "name": "בר",
          "points": 32,
          "matchesPlayed": 28
        },
        {
          "rank": 3,
          "name": "עומר",
          "points": 31,
          "matchesPlayed": 29
        },
        {
          "rank": 4,
          "name": "פרטוש",
          "points": 30,
          "matchesPlayed": 29
        },
        {
          "rank": 5,
          "name": "יניב",
          "points": 29,
          "matchesPlayed": 28
        },
        {
          "rank": 6,
          "name": "עומרי",
          "points": 28,
          "matchesPlayed": 29
        },
        {
          "rank": 7,
          "name": "אריאל",
          "points": 27,
          "matchesPlayed": 32
        },
        {
          "rank": 8,
          "name": "בנימין",
          "points": 26,
          "matchesPlayed": 29
        }
      ]
    },
    {
      "updatedAt": "2026-06-26T04:07:19.370Z",
      "standings": [
        {
          "rank": 1,
          "name": "ניב",
          "points": 33,
          "matchesPlayed": 32
        },
        {
          "rank": 2,
          "name": "בר",
          "points": 32,
          "matchesPlayed": 28
        },
        {
          "rank": 3,
          "name": "עומר",
          "points": 31,
          "matchesPlayed": 29
        },
        {
          "rank": 4,
          "name": "פרטוש",
          "points": 30,
          "matchesPlayed": 30
        },
        {
          "rank": 5,
          "name": "אריאל",
          "points": 29,
          "matchesPlayed": 33
        },
        {
          "rank": 5,
          "name": "יניב",
          "points": 29,
          "matchesPlayed": 28
        },
        {
          "rank": 7,
          "name": "בנימין",
          "points": 28,
          "matchesPlayed": 30
        },
        {
          "rank": 7,
          "name": "עומרי",
          "points": 28,
          "matchesPlayed": 30
        }
      ]
    }
  ]
}
