{
  "updatedAt": "2026-07-02T21:04:23.227Z",
  "matches": [
    {
      "id": "537420",
      "stage": "R32",
      "home": "ספרד",
      "away": "אוסטריה",
      "homeOwners": [
        "עומרי",
        "יניב"
      ],
      "awayOwners": [
        "עומר",
        "פרטוש"
      ],
      "homePoints": 2,
      "awayPoints": 0
    }
  ],
  "deltas": [
    {
      "name": "יניב",
      "points": 2
    },
    {
      "name": "עומרי",
      "points": 2
    }
  ],
  "text": "בעדכון האחרון: יניב +2 (ספרד ניצחה +2) · עומרי +2 (ספרד ניצחה +2)"
}
